{"type":"botania:petal_apothecary","output":{"item":"random-botany:curseater"},"ingredients":[{"item":"minecraft:enchanted_book"},{"tag":"botania:petals/light_gray"},{"tag":"botania:petals/light_gray"},{"tag":"botania:petals/light_gray"},{"tag":"botania:runes/gluttony"},{"tag":"botania:runes/gluttony"},{"tag":"botania:runes/gluttony"},{"tag":"botania:petals/red"},{"tag":"botania:petals/red"},{"tag":"botania:petals/red"},{"tag":"botania:petals/red"},{"tag":"botania:petals/red"},{"tag":"botania:petals/red"},{"tag":"botania:petals/red"}]}